dfschema/__init__.py
dfschema/cli.py
dfschema/core/__init__.py
dfschema/core/collector.py
dfschema/core/column.py
dfschema/core/config.py
dfschema/core/core.py
dfschema/core/dtype.py
dfschema/core/exceptions.py
dfschema/core/generate.py
dfschema/core/legacy/__init__.py
dfschema/core/legacy/v1.py
dfschema/core/logger.py
dfschema/core/metadata.py
dfschema/core/misc.py
dfschema/core/shape.py
dfschema/utils.py
dfschema/validate.py
dfschema-0.0.12.dist-info/entry_points.txt
dfschema-0.0.12.dist-info/LICENSE
dfschema-0.0.12.dist-info/METADATA
dfschema-0.0.12.dist-info/WHEEL
dfschema-0.0.12.dist-info/RECORD
