Metadata-Version: 2.1
Name: dfschema
Version: 0.0.12
Summary: lightweight pandas.DataFrame schema
Author: Philipp
Author-email: philippk@zillowgroup.com
Requires-Python: >=3.8,<4.0
Classifier: Programming Language :: Python :: 3
Classifier: Programming Language :: Python :: 3.8
Classifier: Programming Language :: Python :: 3.9
Classifier: Programming Language :: Python :: 3.10
Classifier: Programming Language :: Python :: 3.11
Classifier: Programming Language :: Python :: 3.12
Provides-Extra: all
Provides-Extra: cli
Provides-Extra: sqlalchemy
Provides-Extra: yaml
Requires-Dist: PyYAML (>=6.0,<7.0) ; extra == "yaml" or extra == "all"
Requires-Dist: pandas (>=1.5.3)
Requires-Dist: pandera (>=0.6,<0.7) ; extra == "all"
Requires-Dist: pydantic (>=2.2,<3.0)
Requires-Dist: sqlalchemy (==1.*) ; extra == "sqlalchemy" or extra == "all"
Requires-Dist: typer (>=0.6.1,<0.7.0) ; extra == "cli" or extra == "all"
